inoio/__init__.py
inoio/errors.py
inoio/serial_connection.py
inoio-0.3.0.dist-info/LICENSE
inoio-0.3.0.dist-info/METADATA
inoio-0.3.0.dist-info/WHEEL
inoio-0.3.0.dist-info/top_level.txt
inoio-0.3.0.dist-info/RECORD
