Metadata-Version: 2.1
Name: inoio
Version: 0.3.0
Summary: Utilities for RX/TX with Arduino devices
Author: David Weber
Classifier: Programming Language :: Python :: 3
Classifier: License :: OSI Approved :: MIT License
Classifier: Operating System :: OS Independent
Requires-Python: >=3.9
License-File: LICENSE
Requires-Dist: pyserial
